aacrgenie-17.0.0.data/scripts/database_to_staging.py
aacrgenie-17.0.0.data/scripts/input_to_database.py
aacrgenie-17.0.0.dist-info/licenses/LICENSE
genie/__init__.py
genie/__main__.py
genie/config.py
genie/consortium_to_public.py
genie/create_case_lists.py
genie/dashboard_table_updater.py
genie/database_to_staging.py
genie/example_filetype_format.py
genie/extract.py
genie/input_to_database.py
genie/load.py
genie/process_functions.py
genie/process_mutation.py
genie/toRetract.py
genie/transform.py
genie/validate.py
genie/write_invalid_reasons.py
genie_registry/__init__.py
genie_registry/assay.py
genie_registry/bed.py
genie_registry/clinical.py
genie_registry/cna.py
genie_registry/maf.py
genie_registry/mutationsInCis.py
genie_registry/patientRetraction.py
genie_registry/sampleRetraction.py
genie_registry/seg.py
genie_registry/structural_variant.py
genie_registry/vcf.py
genie_registry/workflow.py
tests/__init__.py
tests/conftest.py
tests/test_assay.py
tests/test_bed.py
tests/test_clinical.py
tests/test_cna.py
tests/test_create_case_lists.py
tests/test_dashboard_table_updater.py
tests/test_database_to_staging.py
tests/test_example_filetype_format.py
tests/test_extract.py
tests/test_filters.py
tests/test_input_to_database.py
tests/test_load.py
tests/test_maf.py
tests/test_mutations_in_cis.py
tests/test_process_functions.py
tests/test_process_mutation.py
tests/test_retraction.py
tests/test_seg.py
tests/test_sv.py
tests/test_transform.py
tests/test_validate.py
tests/test_vcf.py
tests/test_workflow.py
tests/test_write_invalid_reasons.py
aacrgenie-17.0.0.dist-info/METADATA
aacrgenie-17.0.0.dist-info/WHEEL
aacrgenie-17.0.0.dist-info/entry_points.txt
aacrgenie-17.0.0.dist-info/top_level.txt
aacrgenie-17.0.0.dist-info/RECORD
