Metadata-Version: 2.4
Name: aacrgenie
Version: 17.0.0
Summary: AACR Project GENIE ETL
Home-page: https://github.com/Sage-Bionetworks/Genie
Author: Thomas Yu
Author-email: thomas.yu@sagebionetworks.org
License: MIT
Project-URL: Bug Tracker, https://github.com/Sage-Bionetworks/Genie/issues
Project-URL: Source Code, https://github.com/Sage-Bionetworks/Genie
Platform: any
Classifier: Development Status :: 5 - Production/Stable
Classifier: Environment :: Console
Classifier: Intended Audience :: Science/Research
Classifier: License :: OSI Approved :: MIT License
Classifier: Operating System :: OS Independent
Classifier: Programming Language :: Python
Classifier: Programming Language :: Python :: 3
Classifier: Programming Language :: Python :: 3 :: Only
Classifier: Programming Language :: Python :: 3.10
Classifier: Programming Language :: Python :: 3.11
Classifier: Topic :: Scientific/Engineering
Requires-Python: <3.12,>=3.10
License-File: LICENSE
Requires-Dist: pyranges==0.1.4
Requires-Dist: synapseclient[pandas]<5.0.0,>=4.8.0
Requires-Dist: httplib2>=0.11.3
Requires-Dist: PyYAML>=5.1
Requires-Dist: chardet>=3.0.4
Provides-Extra: dev
Requires-Dist: pytest; extra == "dev"
Requires-Dist: black; extra == "dev"
Requires-Dist: pre-commit; extra == "dev"
Requires-Dist: mypy; extra == "dev"
Provides-Extra: docs
Requires-Dist: mkdocs<=1.6.0; extra == "docs"
Requires-Dist: mkdocs-material<=9.5.23; extra == "docs"
Requires-Dist: mkdocs-open-in-new-tab<=1.0.3; extra == "docs"
Requires-Dist: mkdocstrings<=0.25.1; extra == "docs"
Requires-Dist: mkdocstrings-python<=1.10.2; extra == "docs"
Requires-Dist: griffe<=0.36.3; extra == "docs"
Dynamic: license-file
